waybacklapse/__init__.py
waybacklapse/waybacklapse.py
waybacklapse-1.0.1.dist-info/DESCRIPTION.rst
waybacklapse-1.0.1.dist-info/entry_points.txt
waybacklapse-1.0.1.dist-info/METADATA
waybacklapse-1.0.1.dist-info/metadata.json
waybacklapse-1.0.1.dist-info/RECORD
waybacklapse-1.0.1.dist-info/top_level.txt
waybacklapse-1.0.1.dist-info/WHEEL
